pylproxy/__init__.py
pylproxy/api.py
pylproxy/nginx/docker-compose.yml
pylproxy/nginx/Dockerfile
pylproxy/nginx/nginx.conf
pylproxy/nginx/node_env.env
pylproxy/nginx/yagna/Dockerfile
pylproxy-0.2.3.dist-info/METADATA
pylproxy-0.2.3.dist-info/WHEEL
pylproxy-0.2.3.dist-info/RECORD
